{
	"configurations" : 
	[
		{
			"directories" : 
			[
				{
					"build" : ".",
					"childIndexes" : 
					[
						1,
						2,
						3,
						5,
						6
					],
					"hasInstallRule" : true,
					"jsonFile" : "directory-.-Debug-c4e3cdb4b7d2f6572d1f.json",
					"minimumCMakeVersion" : 
					{
						"string" : "3.14"
					},
					"projectIndex" : 0,
					"source" : "."
				},
				{
					"build" : "flutter",
					"jsonFile" : "directory-flutter-Debug-79e0260f2327d8493c28.json",
					"minimumCMakeVersion" : 
					{
						"string" : "3.14"
					},
					"parentIndex" : 0,
					"projectIndex" : 0,
					"source" : "flutter",
					"targetIndexes" : 
					[
						4,
						5,
						6
					]
				},
				{
					"build" : "runner",
					"jsonFile" : "directory-runner-Debug-86f38b7dcb6f33eb04e4.json",
					"minimumCMakeVersion" : 
					{
						"string" : "3.14"
					},
					"parentIndex" : 0,
					"projectIndex" : 1,
					"source" : "runner",
					"targetIndexes" : 
					[
						1
					]
				},
				{
					"build" : "plugins/dart_vlc",
					"childIndexes" : 
					[
						4
					],
					"jsonFile" : "directory-plugins.dart_vlc-Debug-13f7085b5d21ec881adc.json",
					"minimumCMakeVersion" : 
					{
						"string" : "3.15"
					},
					"parentIndex" : 0,
					"projectIndex" : 2,
					"source" : "flutter/ephemeral/.plugin_symlinks/dart_vlc/windows",
					"targetIndexes" : 
					[
						3
					]
				},
				{
					"build" : "dart_vlc_core",
					"jsonFile" : "directory-dart_vlc_core-Debug-b824a43c3052f2beaa6e.json",
					"minimumCMakeVersion" : 
					{
						"string" : "3.13"
					},
					"parentIndex" : 3,
					"projectIndex" : 3,
					"source" : "flutter/ephemeral/.plugin_symlinks/dart_vlc/dartvlc",
					"targetIndexes" : 
					[
						0,
						2
					]
				},
				{
					"build" : "plugins/url_launcher_windows",
					"jsonFile" : "directory-plugins.url_launcher_windows-Debug-b718b41db8fa69359ace.json",
					"minimumCMakeVersion" : 
					{
						"string" : "3.10"
					},
					"parentIndex" : 0,
					"projectIndex" : 4,
					"source" : "flutter/ephemeral/.plugin_symlinks/url_launcher_windows/windows",
					"targetIndexes" : 
					[
						7
					]
				},
				{
					"build" : "plugins/window_manager",
					"jsonFile" : "directory-plugins.window_manager-Debug-96d174f243515dd0bb1a.json",
					"minimumCMakeVersion" : 
					{
						"string" : "3.15"
					},
					"parentIndex" : 0,
					"projectIndex" : 5,
					"source" : "flutter/ephemeral/.plugin_symlinks/window_manager/windows",
					"targetIndexes" : 
					[
						8
					]
				}
			],
			"name" : "Debug",
			"projects" : 
			[
				{
					"childIndexes" : 
					[
						1,
						2,
						4,
						5
					],
					"directoryIndexes" : 
					[
						0,
						1
					],
					"name" : "animeworldapp",
					"targetIndexes" : 
					[
						4,
						5,
						6
					]
				},
				{
					"directoryIndexes" : 
					[
						2
					],
					"name" : "runner",
					"parentIndex" : 0,
					"targetIndexes" : 
					[
						1
					]
				},
				{
					"childIndexes" : 
					[
						3
					],
					"directoryIndexes" : 
					[
						3
					],
					"name" : "dart_vlc",
					"parentIndex" : 0,
					"targetIndexes" : 
					[
						3
					]
				},
				{
					"directoryIndexes" : 
					[
						4
					],
					"name" : "dart_vlc_core",
					"parentIndex" : 2,
					"targetIndexes" : 
					[
						0,
						2
					]
				},
				{
					"directoryIndexes" : 
					[
						5
					],
					"name" : "url_launcher_windows",
					"parentIndex" : 0,
					"targetIndexes" : 
					[
						7
					]
				},
				{
					"directoryIndexes" : 
					[
						6
					],
					"name" : "window_manager",
					"parentIndex" : 0,
					"targetIndexes" : 
					[
						8
					]
				}
			],
			"targets" : 
			[
				{
					"directoryIndex" : 4,
					"id" : "LIBVLC_EXTRACT::@17184caebe928f5445f4",
					"jsonFile" : "target-LIBVLC_EXTRACT-Debug-3cc2e9e30b38f5ffc2e1.json",
					"name" : "LIBVLC_EXTRACT",
					"projectIndex" : 3
				},
				{
					"directoryIndex" : 2,
					"id" : "animeworldapp::@056c4f61b0156d1d9b06",
					"jsonFile" : "target-animeworldapp-Debug-b8a2aac154f85d3da7eb.json",
					"name" : "animeworldapp",
					"projectIndex" : 1
				},
				{
					"directoryIndex" : 4,
					"id" : "dart_vlc_core::@17184caebe928f5445f4",
					"jsonFile" : "target-dart_vlc_core-Debug-791c9ffa49b6166cfee7.json",
					"name" : "dart_vlc_core",
					"projectIndex" : 3
				},
				{
					"directoryIndex" : 3,
					"id" : "dart_vlc_plugin::@3626ee340483b729c1ae",
					"jsonFile" : "target-dart_vlc_plugin-Debug-0829be16e36a12b0cccc.json",
					"name" : "dart_vlc_plugin",
					"projectIndex" : 2
				},
				{
					"directoryIndex" : 1,
					"id" : "flutter_assemble::@2bb09fbb03a373b2cb34",
					"jsonFile" : "target-flutter_assemble-Debug-7fd3b1731921c52b9299.json",
					"name" : "flutter_assemble",
					"projectIndex" : 0
				},
				{
					"directoryIndex" : 1,
					"id" : "flutter_wrapper_app::@2bb09fbb03a373b2cb34",
					"jsonFile" : "target-flutter_wrapper_app-Debug-f12bf50fc9e6c52222a9.json",
					"name" : "flutter_wrapper_app",
					"projectIndex" : 0
				},
				{
					"directoryIndex" : 1,
					"id" : "flutter_wrapper_plugin::@2bb09fbb03a373b2cb34",
					"jsonFile" : "target-flutter_wrapper_plugin-Debug-87c557c27f80989e0889.json",
					"name" : "flutter_wrapper_plugin",
					"projectIndex" : 0
				},
				{
					"directoryIndex" : 5,
					"id" : "url_launcher_windows_plugin::@82e8e937a0da8e6132e4",
					"jsonFile" : "target-url_launcher_windows_plugin-Debug-d01632507bdd6d72018e.json",
					"name" : "url_launcher_windows_plugin",
					"projectIndex" : 4
				},
				{
					"directoryIndex" : 6,
					"id" : "window_manager_plugin::@5d5a3d495045ca23c295",
					"jsonFile" : "target-window_manager_plugin-Debug-2808697ae1c7209f0155.json",
					"name" : "window_manager_plugin",
					"projectIndex" : 5
				}
			]
		}
	],
	"kind" : "codemodel",
	"paths" : 
	{
		"build" : "C:/Users/info/StudioProjects/animeworldapp/windows/out/build/x64-Debug",
		"source" : "C:/Users/info/StudioProjects/animeworldapp/windows"
	},
	"version" : 
	{
		"major" : 2,
		"minor" : 3
	}
}
